Metadata-Version: 1.1
Name: epipylib
Version: 0.1.0-2
Summary: Epidemic model library for fitting epidemic models.
Home-page: https://github.com/ckaus/epipylib
Author: Christian Kaus
Author-email: christian.kaus@hotmail.de
License: MIT License
Download-URL: http://pypi.python.org/pypi/epipylib
Keywords: epidemic
Platform: Linux
Classifier: Development Status :: 4 - Beta
Classifier: Intended Audience :: Developers
Classifier: Intended Audience :: Education
Classifier: Intended Audience :: Science/Research
Classifier: License :: OSI Approved :: MIT License
Classifier: Natural Language :: English
Classifier: Operating System :: MacOS
Classifier: Operating System :: MacOS :: MacOS X
Classifier: Operating System :: Microsoft
Classifier: Operating System :: Microsoft :: Windows :: Windows 7
Classifier: Operating System :: POSIX
Classifier: Operating System :: POSIX :: Linux
Classifier: Programming Language :: Python
Classifier: Programming Language :: Python :: 2.7
Classifier: Topic :: Documentation
Classifier: Topic :: Documentation :: Sphinx
Classifier: Topic :: Education
Classifier: Topic :: Scientific/Engineering
Classifier: Topic :: Scientific/Engineering :: Bio-Informatics
Classifier: Topic :: Scientific/Engineering :: Information Analysis
Classifier: Topic :: Scientific/Engineering :: Medical Science Apps.
